FOSC/__init__.py
FOSC/cluster.py
FOSC/dendrogram.py
FOSC/fosc.py
FOSC/plot.py
FOSC/utilClasses.py
fosc-0.1.1a1.dist-info/licenses/LICENSE
fosc-0.1.1a1.dist-info/METADATA
fosc-0.1.1a1.dist-info/WHEEL
fosc-0.1.1a1.dist-info/top_level.txt
fosc-0.1.1a1.dist-info/RECORD
