Metadata-Version: 2.4
Name: FOSC
Version: 0.1.1a1
Summary: Framework for Optimal Extraction of Clusters
Home-page: https://github.com/jadsoncastro/FOSC
Author: Jadson Castro Gertrudes
Author-email: jadson.castro@ufop.edu.br
Maintainer: Matheus Neto Gurgel
Maintainer-email: matheus.gurgel@aluno.ufop.edu.br
Classifier: Programming Language :: Python :: 3
Classifier: License :: OSI Approved :: GNU General Public License v3 (GPLv3)
Classifier: Operating System :: OS Independent
Requires-Python: >=3.6
License-File: LICENSE
Requires-Dist: matplotlib==3.8.2
Requires-Dist: mplcursors==0.5.3
Requires-Dist: networkx==3.2.1
Requires-Dist: numpy==1.26.2
Requires-Dist: scipy==1.11.4
Requires-Dist: typing_extensions==4.12.2
Dynamic: author
Dynamic: author-email
Dynamic: classifier
Dynamic: description
Dynamic: description-content-type
Dynamic: home-page
Dynamic: license-file
Dynamic: maintainer
Dynamic: maintainer-email
Dynamic: requires-dist
Dynamic: requires-python
Dynamic: summary
